CleanFlow-1.0.5a1.dist-info/DESCRIPTION.rst
CleanFlow-1.0.5a1.dist-info/METADATA
CleanFlow-1.0.5a1.dist-info/RECORD
CleanFlow-1.0.5a1.dist-info/WHEEL
CleanFlow-1.0.5a1.dist-info/metadata.json
CleanFlow-1.0.5a1.dist-info/top_level.txt
cleanflow/__init__.py
cleanflow/assertions.py
cleanflow/spark.py
cleanflow/exploratory/__init__.py
cleanflow/exploratory/describe.py
cleanflow/exploratory/duplicates.py
cleanflow/getOutput/__init__.py
cleanflow/getOutput/to_csv.py
cleanflow/preprocessing/__init__.py
cleanflow/preprocessing/drop_col.py
cleanflow/preprocessing/impute_missing.py
cleanflow/preprocessing/lower_case.py
cleanflow/preprocessing/remove_duplicates.py
cleanflow/preprocessing/replace_na.py
cleanflow/preprocessing/rmSpChars.py
cleanflow/preprocessing/set_col.py
cleanflow/preprocessing/trim_col.py
cleanflow/preprocessing/upper_case.py
